qaa/__init__.py
qaa/__main__.py
qaa/cli.py
qaa/commands/__init__.py
qaa/commands/cmd_align.py
qaa/commands/cmd_cluster.py
qaa/commands/cmd_pca.py
qaa/commands/cmd_plot.py
qaa/commands/cmd_qaa.py
qaa/decomposition/__init__.py
qaa/decomposition/jade.py
qaa/libs/__init__.py
qaa/libs/align.py
qaa/libs/figure.py
qaa/libs/kabsch.py
qaa/libs/utils.py
qaa/py.typed
qaa-3.0.0rc3.dist-info/entry_points.txt
qaa-3.0.0rc3.dist-info/LICENSE.rst
qaa-3.0.0rc3.dist-info/WHEEL
qaa-3.0.0rc3.dist-info/METADATA
qaa-3.0.0rc3.dist-info/RECORD
