Metadata-Version: 2.1
Name: qaa
Version: 3.0.0rc3
Summary: Quasi-Anharmonic Analysis
Home-page: https://github.com/tclick/qaa
License: BSD-3-Clause
Author: Timothy H. Click
Author-email: tclick@okstate.edu
Requires-Python: >=3.7, !=2.7.*, !=3.0.*, !=3.1.*, !=3.2.*, !=3.3.*, !=3.4.*, !=3.5.*, !=3.6.*
Classifier: License :: OSI Approved :: BSD License
Classifier: Programming Language :: Python :: 3
Classifier: Programming Language :: Python :: 3.7
Classifier: Programming Language :: Python :: 3.9
Provides-Extra: jupyter
Requires-Dist: click (>=7.0,<8.0)
Requires-Dist: holoviews[recommended] (>=1.14.3,<2.0.0)
Requires-Dist: ipykernel (>=5.5.3,<6.0.0)
Requires-Dist: jupyter (>=1.0.0,<2.0.0); extra == "jupyter"
Requires-Dist: jupyterlab (>=3.0.13,<4.0.0); extra == "jupyter"
Requires-Dist: jupyterlab-code-formatter (>=1.4.10,<2.0.0); extra == "jupyter"
Requires-Dist: jupyterlab-mathjax3 (>=4.2.2,<5.0.0); extra == "jupyter"
Requires-Dist: mdtraj (>=1.9,<2.0)
Requires-Dist: nglview (>=3.0.0,<4.0.0); extra == "jupyter"
Requires-Dist: nptyping (>=1.4,<2.0)
Requires-Dist: plotly (>=4.14.3,<5.0.0); extra == "jupyter"
Requires-Dist: scikit-learn (>=0.24,<0.25)
Project-URL: Changelog, https://github.com/tclick/qaa/releases
Project-URL: Documentation, https://pyqaa.readthedocs.io
Project-URL: Repository, https://github.com/tclick/qaa
